setup.py
vwoptimize.py
vwoptimize.egg-info/PKG-INFO
vwoptimize.egg-info/SOURCES.txt
vwoptimize.egg-info/dependency_links.txt
vwoptimize.egg-info/top_level.txt
vwoptimizelib/__init__.py
vwoptimizelib/third_party/__init__.py
vwoptimizelib/third_party/decorator.py
vwoptimizelib/third_party/hyperopt/__init__.py
vwoptimizelib/third_party/hyperopt/algobase.py
vwoptimizelib/third_party/hyperopt/anneal.py
vwoptimizelib/third_party/hyperopt/base.py
vwoptimizelib/third_party/hyperopt/criteria.py
vwoptimizelib/third_party/hyperopt/exceptions.py
vwoptimizelib/third_party/hyperopt/fmin.py
vwoptimizelib/third_party/hyperopt/graphviz.py
vwoptimizelib/third_party/hyperopt/hp.py
vwoptimizelib/third_party/hyperopt/ipy.py
vwoptimizelib/third_party/hyperopt/main.py
vwoptimizelib/third_party/hyperopt/mix.py
vwoptimizelib/third_party/hyperopt/mongoexp.py
vwoptimizelib/third_party/hyperopt/plotting.py
vwoptimizelib/third_party/hyperopt/pyll_utils.py
vwoptimizelib/third_party/hyperopt/rand.py
vwoptimizelib/third_party/hyperopt/rdists.py
vwoptimizelib/third_party/hyperopt/tpe.py
vwoptimizelib/third_party/hyperopt/utils.py
vwoptimizelib/third_party/hyperopt/vectorize.py
vwoptimizelib/third_party/hyperopt/pyll/__init__.py
vwoptimizelib/third_party/hyperopt/pyll/base.py
vwoptimizelib/third_party/hyperopt/pyll/stochastic.py
vwoptimizelib/third_party/networkx/__init__.py
vwoptimizelib/third_party/networkx/convert.py
vwoptimizelib/third_party/networkx/convert_matrix.py
vwoptimizelib/third_party/networkx/exception.py
vwoptimizelib/third_party/networkx/relabel.py
vwoptimizelib/third_party/networkx/release.py
vwoptimizelib/third_party/networkx/version.py
vwoptimizelib/third_party/networkx/algorithms/__init__.py
vwoptimizelib/third_party/networkx/algorithms/block.py
vwoptimizelib/third_party/networkx/algorithms/boundary.py
vwoptimizelib/third_party/networkx/algorithms/clique.py
vwoptimizelib/third_party/networkx/algorithms/cluster.py
vwoptimizelib/third_party/networkx/algorithms/core.py
vwoptimizelib/third_party/networkx/algorithms/cycles.py
vwoptimizelib/third_party/networkx/algorithms/dag.py
