Metadata-Version: 1.0
Name: vwoptimize
Version: 0.10.2
Summary: Hyper-parameter search, text preprocessing and reporting for Vowpal Wabbit
Home-page: https://github.com/denik/vwoptimize
Author: Denis Bilenko
Author-email: denis.bilenko@gmail.com
License: UNKNOWN
Platform: UNKNOWN
